{
  "numFound": 286329,
  "torrentList": [
    {
      "fid": "241658638",
      "filename": "Rabbit.Trap.2025.1080p.BluRay.REMUX.AVC.DTS-HD.MA.5.1-PiRAMiDHEAD.torrent",
      "name": "Rabbit Trap 2025 1080p BluRay REMUX AVC DTS-HD MA 5 1-PiRAMiDHEAD",
      "addedTimestamp": "2025-12-10 00:50:46",
      "categoryID": 13,
      "size": 19401273503,
      "completed": 367,
      "seeders": 36,
      "leechers": 0,
      "numComments": 0,
      "tags": [
        "FREELEECH",
        "Horror",
        "Mystery"
      ],
      "new": false,
      "imdbID": "tt29567402",
      "rating": 4.8,
      "genres": "Horror, Mystery",
      "tvmazeID": "",
      "igdbID": "",
      "animeID": "",
      "download_multiplier": 0,
      "commentsDisabled": 0
    },
    {
      "fid": "241658637",
      "filename": "The.Secret.Lives.of.Mormon.Wives.S03.REPACK.2160p.DSNP.WEB-DL.DD+.5.1.H.265-BLOOM.torrent",
      "name": "The Secret Lives of Mormon Wives S03 REPACK 2160p DSNP WEB-DL DD+ 5 1 H 265-BLOOM",
      "addedTimestamp": "2025-12-10 00:50:43",
      "categoryID": 27,
      "size": 51077171122,
      "completed": 63,
      "seeders": 20,
      "leechers": 0,
      "numComments": 0,
      "tags": [
        "FREELEECH"
      ],
      "new": false,
      "imdbID": "",
      "rating": 0,
      "genres": "",
      "tvmazeID": "s78970",
      "igdbID": "",
      "animeID": "",
      "download_multiplier": 0,
      "commentsDisabled": 0
    },
    {
      "fid": "241658630",
      "filename": "Law.and.Order.S24.1080p.x265-ELiTE.torrent",
      "name": "Law and Order S24 1080p x265-ELiTE",
      "addedTimestamp": "2025-12-10 00:38:01",
      "categoryID": 27,
      "size": 16252873359,
      "completed": 242,
      "seeders": 13,
      "leechers": 0,
      "numComments": 0,
      "tags": [
        "1080p",
        "ELiTE",
        "FREELEECH"
      ],
      "new": false,
      "imdbID": "tt0098844",
      "rating": 7.8,
      "genres": "Crime, Drama, Mystery, Thriller",
      "tvmazeID": "s562",
      "igdbID": "",
      "animeID": "",
      "download_multiplier": 0,
      "commentsDisabled": 0
    },
    {
      "fid": "241658629",
      "filename": "Law.and.Order.S24.720p.x265-TiPEX.torrent",
      "name": "Law and Order S24 720p x265-TiPEX",
      "addedTimestamp": "2025-12-10 00:31:09",
      "categoryID": 27,
      "size": 9393858919,
      "completed": 199,
      "seeders": 8,
      "leechers": 0,
      "numComments": 0,
      "tags": [
        "720p",
        "FREELEECH",
        "TiPEX"
      ],
      "new": false,
      "imdbID": "tt0098844",
      "rating": 7.8,
      "genres": "Crime, Drama, Mystery, Thriller",
      "tvmazeID": "s562",
      "igdbID": "",
      "animeID": "",
      "download_multiplier": 0,
      "commentsDisabled": 0
    },
    {
      "fid": "241658627",
      "filename": "The.Boulet.Brothers.Dragula.Titans.(2022).S02.1080p.WEB.x265.torrent",
      "name": "The Boulet Brothers Dragula Titans (2022) S02 1080p WEB x265",
      "addedTimestamp": "2025-12-10 00:28:37",
      "categoryID": 27,
      "size": 11346248033,
      "completed": 260,
      "seeders": 18,
      "leechers": 1,
      "numComments": 0,
      "tags": [
        "FREELEECH"
      ],
      "new": false,
      "imdbID": "",
      "rating": 0,
      "genres": "",
      "tvmazeID": "s64170",
      "igdbID": "",
      "animeID": "",
      "download_multiplier": 0,
      "commentsDisabled": 0
    },
    {
      "fid": "241658624",
      "filename": "Blown.Away.(1994).BluRay.1080p.REMUX.AVC.DTS-HD.MA.5.1.torrent",
      "name": "Blown Away (1994) BluRay 1080p REMUX AVC DTS-HD MA 5 1",
      "addedTimestamp": "2025-12-10 00:03:37",
      "categoryID": 13,
      "size": 38649967937,
      "completed": 261,
      "seeders": 10,
      "leechers": 0,
      "numComments": 0,
      "tags": [
        "Action",
        "Crime",
        "Drama",
        "FREELEECH",
        "Thriller"
      ],
      "new": false,
      "imdbID": "tt0109303",
      "rating": 6.1,
      "genres": "Action, Crime, Drama, Thriller",
      "tvmazeID": "",
      "igdbID": "",
      "animeID": "",
      "download_multiplier": 0,
      "commentsDisabled": 0
    },
    {
      "fid": "241658621",
      "filename": "The.Summit..2017.1080p.BluRay.REMUX.AVC.TrueHD.EX.5.1-FraMeSToR.torrent",
      "name": "The Summit  2017 1080p BluRay REMUX AVC TrueHD EX 5 1-FraMeSToR",
      "addedTimestamp": "2025-12-09 23:29:26",
      "categoryID": 36,
      "size": 26221326702,
      "completed": 128,
      "seeders": 4,
      "leechers": 0,
      "numComments": 0,
      "tags": [
        "Drama",
        "FREELEECH",
        "Mystery",
        "Thriller"
      ],
      "new": false,
      "imdbID": "tt6047298",
      "rating": 6,
      "genres": "Drama, Mystery, Thriller",
      "tvmazeID": "",
      "igdbID": "",
      "animeID": "",
      "download_multiplier": 0,
      "commentsDisabled": 0
    },
    {
      "fid": "241658619",
      "filename": "The.Shrine.2010.1080p.BluRay.REMUX.AVC.DTS-HD.MA.5.1-BLURANiUM.torrent",
      "name": "The Shrine 2010 1080p BluRay REMUX AVC DTS-HD MA 5 1-BLURANiUM",
      "addedTimestamp": "2025-12-09 23:11:53",
      "categoryID": 13,
      "size": 17250546880,
      "completed": 179,
      "seeders": 12,
      "leechers": 0,
      "numComments": 0,
      "tags": [
        "FREELEECH",
        "Horror"
      ],
      "new": false,
      "imdbID": "tt1341710",
      "rating": 5.5,
      "genres": "Horror",
      "tvmazeID": "",
      "igdbID": "",
      "animeID": "",
      "download_multiplier": 0,
      "commentsDisabled": 0
    },
    {
      "fid": "241658618",
      "filename": "Warhammer.40000.Space.Marine.2.v11.1.0.1.REPACK-KaOs.torrent",
      "name": "Warhammer 40000 Space Marine 2 v11 1 0 1 REPACK-KaOs",
      "addedTimestamp": "2025-12-09 23:10:42",
      "categoryID": 17,
      "size": 55789059158,
      "completed": 284,
      "seeders": 13,
      "leechers": 0,
      "numComments": 0,
      "tags": [
        "Adventure",
        "FREELEECH",
        "Role-playing (RPG)",
        "Shooter"
      ],
      "new": false,
      "imdbID": "",
      "rating": 0,
      "genres": "",
      "tvmazeID": "",
      "igdbID": 185252,
      "animeID": "",
      "download_multiplier": 0,
      "commentsDisabled": 0
    },
    {
      "fid": "241658617",
      "filename": "Mrs.Browns.Boys.D.Movie.2014.1080p.BluRay.H264-RMX.torrent",
      "name": "Mrs Browns Boys D Movie 2014 1080p BluRay H264-RMX",
      "addedTimestamp": "2025-12-09 23:07:41",
      "categoryID": 14,
      "size": 23607524357,
      "completed": 195,
      "seeders": 3,
      "leechers": 1,
      "numComments": 0,
      "tags": [
        "comedy",
        "FREELEECH"
      ],
      "new": false,
      "imdbID": "tt3433074",
      "rating": 4,
      "genres": "Comedy",
      "tvmazeID": "",
      "igdbID": "",
      "animeID": "",
      "download_multiplier": 0,
      "commentsDisabled": 0
    },
    {
      "fid": "241658616",
      "filename": "The.Honeymoon.Killers.1970.Criterion.1080p.BluRay.REMUX.AVC.LPCM.1.0-UBits.torrent",
      "name": "The Honeymoon Killers 1970 Criterion 1080p BluRay REMUX AVC LPCM 1 0-UBits",
      "addedTimestamp": "2025-12-09 23:06:37",
      "categoryID": 13,
      "size": 29371746636,
      "completed": 231,
      "seeders": 9,
      "leechers": 0,
      "numComments": 0,
      "tags": [
        "Crime",
        "Drama",
        "FREELEECH",
        "Romance",
        "Thriller"
      ],
      "new": false,
      "imdbID": "tt0064437",
      "rating": 7.1,
      "genres": "Crime, Drama, Romance, Thriller",
      "tvmazeID": "",
      "igdbID": "",
      "animeID": "",
      "download_multiplier": 0,
      "commentsDisabled": 0
    },
    {
      "fid": "241658615",
      "filename": "A.Confession.2019.S01.NORDiC.1080p.WEB-DL.H.264-BlowMe.torrent",
      "name": "A Confession 2019 S01 NORDiC 1080p WEB-DL H 264-BlowMe",
      "addedTimestamp": "2025-12-09 23:05:28",
      "categoryID": 27,
      "size": 9757784508,
      "completed": 345,
      "seeders": 27,
      "leechers": 0,
      "numComments": 0,
      "tags": [
        "Biography",
        "Crime",
        "Drama",
        "FREELEECH"
      ],
      "new": false,
      "imdbID": "tt9131050",
      "rating": 7.6,
      "genres": "Biography, Crime, Drama",
      "tvmazeID": "s39235",
      "igdbID": "",
      "animeID": "",
      "download_multiplier": 0,
      "commentsDisabled": 0
    },
    {
      "fid": "241658614",
      "filename": "Metro.Manila.2013.1080p.BluRay.REMUX.AVC.DTS-HD.MA.5.1-FraMeSToR.torrent",
      "name": "Metro Manila 2013 1080p BluRay REMUX AVC DTS-HD MA 5 1-FraMeSToR",
      "addedTimestamp": "2025-12-09 22:54:53",
      "categoryID": 36,
      "size": 29178998000,
      "completed": 103,
      "seeders": 7,
      "leechers": 0,
      "numComments": 0,
      "tags": [
        "Action",
        "Crime",
        "Drama",
        "FREELEECH",
        "Thriller"
      ],
      "new": false,
      "imdbID": "tt1845838",
      "rating": 7.5,
      "genres": "Action, Crime, Drama, Thriller",
      "tvmazeID": "",
      "igdbID": "",
      "animeID": "",
      "download_multiplier": 0,
      "commentsDisabled": 0
    },
    {
      "fid": "241658612",
      "filename": "American.Dad.(2005).S15.(1080p.DSNP.Webrip.x265.10bit.EAC3.5.1.-.Goki)[TAoE].torrent",
      "name": "American Dad (2005) S15 (1080p DSNP Webrip x265 10bit EAC3 5 1 - Goki)[TAoE]",
      "addedTimestamp": "2025-12-09 22:49:48",
      "categoryID": 27,
      "size": 3636257405,
      "completed": 344,
      "seeders": 50,
      "leechers": 0,
      "numComments": 0,
      "tags": [
        "FREELEECH"
      ],
      "new": false,
      "imdbID": "",
      "rating": 0,
      "genres": "",
      "tvmazeID": "s215",
      "igdbID": "",
      "animeID": "",
      "download_multiplier": 0,
      "commentsDisabled": 0
    },
    {
      "fid": "241658610",
      "filename": "A.Perfect.Planet.(2020).S01.(1080p.BluRay.x265.HEVC.10bit.AAC.7.1.Silence).[QxR].torrent",
      "name": "A Perfect Planet (2020) S01 (1080p BluRay x265 HEVC 10bit AAC 7 1 Silence) [QxR]",
      "addedTimestamp": "2025-12-09 22:46:17",
      "categoryID": 27,
      "size": 18496776429,
      "completed": 116,
      "seeders": 7,
      "leechers": 0,
      "numComments": 0,
      "tags": [
        "Action",
        "Adventure",
        "comedy",
        "FREELEECH"
      ],
      "new": false,
      "imdbID": "",
      "rating": 0,
      "genres": "",
      "tvmazeID": "s52683",
      "igdbID": "",
      "animeID": "",
      "download_multiplier": 0,
      "commentsDisabled": 0
    },
    {
      "fid": "241658609",
      "filename": "Storage.Wars.Texas.S04.720p.WebDL.x264-CallMeBrado.torrent",
      "name": "Storage Wars Texas S04 720p WebDL x264-CallMeBrado",
      "addedTimestamp": "2025-12-09 22:38:48",
      "categoryID": 27,
      "size": 19278005608,
      "completed": 98,
      "seeders": 2,
      "leechers": 1,
      "numComments": 0,
      "tags": [
        "FREELEECH"
      ],
      "new": false,
      "imdbID": "",
      "rating": 0,
      "genres": "",
      "tvmazeID": "s4205",
      "igdbID": "",
      "animeID": "",
      "download_multiplier": 0,
      "commentsDisabled": 0,
      "uploader": "pitchou"
    },
    {
      "fid": "241658608",
      "filename": "Inconceivable.2017.1080p.BluRay.REMUX.AVC.DTS-HD.MA.5.1-FraMeSToR.torrent",
      "name": "Inconceivable 2017 1080p BluRay REMUX AVC DTS-HD MA 5 1-FraMeSToR",
      "addedTimestamp": "2025-12-09 22:36:36",
      "categoryID": 13,
      "size": 30378643747,
      "completed": 152,
      "seeders": 5,
      "leechers": 0,
      "numComments": 0,
      "tags": [
        "Drama",
        "FREELEECH",
        "Thriller"
      ],
      "new": false,
      "imdbID": "tt3481634",
      "rating": 5.2,
      "genres": "Drama, Thriller",
      "tvmazeID": "",
      "igdbID": "",
      "animeID": "",
      "download_multiplier": 0,
      "commentsDisabled": 0
    },
    {
      "fid": "241658606",
      "filename": "The.Prince.of.Tennis.S01.1080p.CR.WEB-DL.AAC2.0.H.264-FUZEER.torrent",
      "name": "The Prince of Tennis S01 1080p CR WEB-DL AAC2 0 H 264-FUZEER",
      "addedTimestamp": "2025-12-09 22:35:30",
      "categoryID": 27,
      "size": 180671911223,
      "completed": 53,
      "seeders": 2,
      "leechers": 0,
      "numComments": 0,
      "tags": [
        "Anime",
        "comedy",
        "FREELEECH",
        "Sports"
      ],
      "new": false,
      "imdbID": "",
      "rating": 0,
      "genres": "",
      "tvmazeID": "s17126",
      "igdbID": "",
      "animeID": "",
      "download_multiplier": 0,
      "commentsDisabled": 0
    },
    {
      "fid": "241658605",
      "filename": "The.Prestige.2006.COMPLETE.BLURAY.iNTERNAL-OLDHAM.torrent",
      "name": "The Prestige 2006 COMPLETE BLURAY iNTERNAL-OLDHAM",
      "addedTimestamp": "2025-12-09 22:27:46",
      "categoryID": 13,
      "size": 43259940497,
      "completed": 96,
      "seeders": 4,
      "leechers": 0,
      "numComments": 0,
      "tags": [
        "Drama",
        "FREELEECH",
        "Mystery",
        "Sci-Fi"
      ],
      "new": false,
      "imdbID": "tt0482571",
      "rating": 8.5,
      "genres": "Drama, Mystery, Sci-Fi",
      "tvmazeID": "",
      "igdbID": "",
      "animeID": "",
      "download_multiplier": 0,
      "commentsDisabled": 0
    },
    {
      "fid": "241658600",
      "filename": "The.Last.Frontier.2025.S01.2160p.WEBRip.x265.10bit.DV.HDR10Plus.DDP5.1.Atmos-KONTRAST.torrent",
      "name": "The Last Frontier 2025 S01 2160p WEBRip x265 10bit DV HDR10Plus DDP5 1 Atmos-KONTRAST",
      "addedTimestamp": "2025-12-09 22:21:22",
      "categoryID": 27,
      "size": 36293537590,
      "completed": 134,
      "seeders": 9,
      "leechers": 0,
      "numComments": 0,
      "tags": [
        "Action",
        "Drama",
        "FREELEECH",
        "Thriller"
      ],
      "new": false,
      "imdbID": "tt26862142",
      "rating": 6.7,
      "genres": "Action, Drama, Thriller",
      "tvmazeID": "s67154",
      "igdbID": "",
      "animeID": "",
      "download_multiplier": 0,
      "commentsDisabled": 0
    },
    {
      "fid": "241658594",
      "filename": "Alone.Germany.S01.SUBBED.1080p.HDTV.H264-CBFM.torrent",
      "name": "Alone Germany S01 SUBBED 1080p HDTV H264-CBFM",
      "addedTimestamp": "2025-12-09 22:17:40",
      "categoryID": 44,
      "size": 19551664848,
      "completed": 116,
      "seeders": 9,
      "leechers": 0,
      "numComments": 0,
      "tags": [
        "Adventure",
        "Documentary",
        "FREELEECH",
        "Game-Show",
        "nature",
        "Reality-TV"
      ],
      "new": false,
      "imdbID": "tt30317224",
      "rating": 6.8,
      "genres": "Documentary, Game-Show, Reality-TV",
      "tvmazeID": "s82284",
      "igdbID": "",
      "animeID": "",
      "download_multiplier": 0,
      "commentsDisabled": 0
    },
    {
      "fid": "241658590",
      "filename": "The.Naked.Gun.From.the.Files.of.Police.Squad!.1988.1080p.CAN.Blu-ray.AVC.DTS-HD.MA.5.1-nukmasta.torrent",
      "name": "The Naked Gun From the Files of Police Squad! 1988 1080p CAN Blu-ray AVC DTS-HD MA 5.1-nukmasta",
      "addedTimestamp": "2025-12-09 22:14:00",
      "categoryID": 13,
      "size": 27531217836,
      "completed": 141,
      "seeders": 3,
      "leechers": 0,
      "numComments": 0,
      "tags": [
        "Action",
        "comedy",
        "Crime",
        "FREELEECH",
        "Romance"
      ],
      "new": false,
      "imdbID": "tt0095705",
      "rating": 7.6,
      "genres": "Action, Comedy, Crime, Romance",
      "tvmazeID": "",
      "igdbID": "",
      "animeID": "",
      "download_multiplier": 0,
      "commentsDisabled": 0
    },
    {
      "fid": "241658588",
      "filename": "Dragon.Fist..1979.Hybrid.PROPER.1080p.BluRay.REMUX.AVC.DTS-HD.MA.5.1-FraMeSToR.torrent",
      "name": "Dragon Fist  1979 Hybrid PROPER 1080p BluRay REMUX AVC DTS-HD MA 5 1-FraMeSToR",
      "addedTimestamp": "2025-12-09 22:12:59",
      "categoryID": 36,
      "size": 33897448501,
      "completed": 156,
      "seeders": 6,
      "leechers": 0,
      "numComments": 0,
      "tags": [
        "Action",
        "Drama",
        "FREELEECH"
      ],
      "new": false,
      "imdbID": "tt0079484",
      "rating": 6.3,
      "genres": "Action, Drama",
      "tvmazeID": "",
      "igdbID": "",
      "animeID": "",
      "download_multiplier": 0,
      "commentsDisabled": 0
    },
    {
      "fid": "241658565",
      "filename": "The.Last.Frontier.2025.S01.1080p.WEBRip.x265-KONTRAST.torrent",
      "name": "The Last Frontier 2025 S01 1080p WEBRip x265-KONTRAST",
      "addedTimestamp": "2025-12-09 21:48:18",
      "categoryID": 27,
      "size": 13171475595,
      "completed": 251,
      "seeders": 24,
      "leechers": 0,
      "numComments": 0,
      "tags": [
        "Action",
        "Drama",
        "FREELEECH",
        "Thriller"
      ],
      "new": false,
      "imdbID": "tt26862142",
      "rating": 6.7,
      "genres": "Action, Drama, Thriller",
      "tvmazeID": "s67154",
      "igdbID": "",
      "animeID": "",
      "download_multiplier": 0,
      "commentsDisabled": 0
    },
    {
      "fid": "241658537",
      "filename": "Chainsaw.Man.The.Movie.Reze.Arc.2025.REPACK.2160p.MA.WEB-DL.DUAL.DDP5.1.Atmos.DV.HDR10P.H.265-BYNDR.torrent",
      "name": "Chainsaw Man The Movie Reze Arc 2025 REPACK 2160p MA WEB-DL DUAL DDP5 1 Atmos DV HDR10P H 265-BYNDR",
      "addedTimestamp": "2025-12-09 20:58:19",
      "categoryID": 34,
      "size": 19228357612,
      "completed": 526,
      "seeders": 113,
      "leechers": 0,
      "numComments": 2,
      "tags": [
        "Action",
        "Drama",
        "FREELEECH",
        "Horror",
        "Romance",
        "supernatural"
      ],
      "new": false,
      "imdbID": "",
      "rating": 0,
      "genres": "",
      "tvmazeID": "",
      "igdbID": "",
      "animeID": 171627,
      "download_multiplier": 0,
      "commentsDisabled": 0
    },
    {
      "fid": "241658536",
      "filename": "Star.Wars.Young.Jedi.Adventures.S03.2160p.DSNP.WEB-DL.DDP5.1.HDR.H.265-STC.torrent",
      "name": "Star Wars Young Jedi Adventures S03 2160p DSNP WEB-DL DDP5 1 HDR H 265-STC",
      "addedTimestamp": "2025-12-09 20:45:49",
      "categoryID": 27,
      "size": 17830658971,
      "completed": 159,
      "seeders": 8,
      "leechers": 0,
      "numComments": 0,
      "tags": [
        "Adventure",
        "Children",
        "FREELEECH",
        "Science-Fiction"
      ],
      "new": false,
      "imdbID": "",
      "rating": 0,
      "genres": "",
      "tvmazeID": "s62296",
      "igdbID": "",
      "animeID": "",
      "download_multiplier": 0,
      "commentsDisabled": 0,
      "uploader": "FooKaS"
    },
    {
      "fid": "241658535",
      "filename": "My.Brilliant.Friend.AKA.L.amica.geniale.S01-S04.MAX.720p.WEB-DL.DDP5.1.x264-iYi.torrent",
      "name": "My Brilliant Friend AKA L amica geniale S01-S04 MAX 720p WEB-DL DDP5 1 x264-iYi",
      "addedTimestamp": "2025-12-09 20:36:42",
      "categoryID": 44,
      "size": 25899827005,
      "completed": 92,
      "seeders": 0,
      "leechers": 0,
      "numComments": 1,
      "tags": [
        "FREELEECH"
      ],
      "new": false,
      "imdbID": "",
      "rating": 0,
      "genres": "",
      "tvmazeID": "s38058",
      "igdbID": "",
      "animeID": "",
      "download_multiplier": 0,
      "commentsDisabled": 0,
      "uploader": "Fr33dom"
    },
    {
      "fid": "241658532",
      "filename": "Star.Wars.Young.Jedi.Adventures.S03.2160p.DSNP.WEB-DL.DDP5.1.DV.H.265-STC.torrent",
      "name": "Star Wars Young Jedi Adventures S03 2160p DSNP WEB-DL DDP5 1 DV H 265-STC",
      "addedTimestamp": "2025-12-09 20:17:37",
      "categoryID": 27,
      "size": 20650818500,
      "completed": 128,
      "seeders": 5,
      "leechers": 0,
      "numComments": 0,
      "tags": [
        "Adventure",
        "Children",
        "FREELEECH",
        "Science-Fiction"
      ],
      "new": false,
      "imdbID": "",
      "rating": 0,
      "genres": "",
      "tvmazeID": "s62296",
      "igdbID": "",
      "animeID": "",
      "download_multiplier": 0,
      "commentsDisabled": 0,
      "uploader": "FooKaS"
    },
    {
      "fid": "241658530",
      "filename": "Wolf.Man.2025.2160p.UHD.BluRay.TrueHD.Atmos.7.1.HDR.x265-j3rico.torrent",
      "name": "Wolf Man 2025 2160p UHD BluRay TrueHD Atmos 7 1 HDR x265-j3rico",
      "addedTimestamp": "2025-12-09 20:13:42",
      "categoryID": 47,
      "size": 22553976444,
      "completed": 250,
      "seeders": 25,
      "leechers": 0,
      "numComments": 0,
      "tags": [
        "FREELEECH",
        "Horror"
      ],
      "new": false,
      "imdbID": "tt4216984",
      "rating": 5.6,
      "genres": "Horror",
      "tvmazeID": "",
      "igdbID": "",
      "animeID": "",
      "download_multiplier": 0,
      "commentsDisabled": 0,
      "uploader": "j3rico"
    },
    {
      "fid": "241658528",
      "filename": "The.Unholy.Trinity.(2024).1080p.BluRay.REMUX.Dts-HDMa5.1.AVC-d3g.torrent",
      "name": "The Unholy Trinity (2024) 1080p BluRay REMUX Dts-HDMa5 1 AVC-d3g",
      "addedTimestamp": "2025-12-09 20:09:37",
      "categoryID": 13,
      "size": 27606187174,
      "completed": 149,
      "seeders": 7,
      "leechers": 0,
      "numComments": 0,
      "tags": [
        "Action",
        "Adventure",
        "Crime",
        "FREELEECH"
      ],
      "new": false,
      "imdbID": "tt6300910",
      "rating": 5.5,
      "genres": "Action, Adventure, Crime",
      "tvmazeID": "",
      "igdbID": "",
      "animeID": "",
      "download_multiplier": 0,
      "commentsDisabled": 0,
      "uploader": "PieR8"
    },
    {
      "fid": "241658526",
      "filename": "Minority.Report.2002.2160p.UHD.BluRay.H265-GAZPROM.torrent",
      "name": "Minority Report 2002 2160p UHD BluRay H265-GAZPROM",
      "addedTimestamp": "2025-12-09 20:03:40",
      "categoryID": 47,
      "size": 87561256184,
      "completed": 79,
      "seeders": 1,
      "leechers": 0,
      "numComments": 0,
      "tags": [
        "Action",
        "Crime",
        "FREELEECH",
        "Mystery"
      ],
      "new": false,
      "imdbID": "tt0181689",
      "rating": 7.6,
      "genres": "Action, Crime, Mystery",
      "tvmazeID": "",
      "igdbID": "",
      "animeID": "",
      "download_multiplier": 0,
      "commentsDisabled": 0
    },
    {
      "fid": "241658524",
      "filename": "Tales.From.the.Crypt.Demon.Knight.(1995).1080p.BluRay.REMUX.Dts-HDMa5.1.AVC-d3g.torrent",
      "name": "Tales From the Crypt Demon Knight (1995) 1080p BluRay REMUX Dts-HDMa5 1 AVC-d3g",
      "addedTimestamp": "2025-12-09 19:58:28",
      "categoryID": 13,
      "size": 27642972601,
      "completed": 102,
      "seeders": 5,
      "leechers": 0,
      "numComments": 0,
      "tags": [
        "Action",
        "FREELEECH",
        "Horror",
        "Thriller"
      ],
      "new": false,
      "imdbID": "tt0114608",
      "rating": 6.7,
      "genres": "Action, Horror, Thriller",
      "tvmazeID": "",
      "igdbID": "",
      "animeID": "",
      "download_multiplier": 0,
      "commentsDisabled": 0,
      "uploader": "PieR8"
    },
    {
      "fid": "241658523",
      "filename": "House.of.David.S02.1080p.WEBRip.x265-KONTRAST.torrent",
      "name": "House of David S02 1080p WEBRip x265-KONTRAST",
      "addedTimestamp": "2025-12-09 19:58:06",
      "categoryID": 27,
      "size": 10856747036,
      "completed": 204,
      "seeders": 29,
      "leechers": 0,
      "numComments": 0,
      "tags": [
        "Drama",
        "FREELEECH"
      ],
      "new": false,
      "imdbID": "tt30955673",
      "rating": 7.4,
      "genres": "History",
      "tvmazeID": "s78124",
      "igdbID": "",
      "animeID": "",
      "download_multiplier": 0,
      "commentsDisabled": 0
    },
    {
      "fid": "241658522",
      "filename": "Death.by.Lightning.S01.1080p.WEBRip.x265-KONTRAST.torrent",
      "name": "Death by Lightning S01 1080p WEBRip x265-KONTRAST",
      "addedTimestamp": "2025-12-09 19:56:38",
      "categoryID": 27,
      "size": 5214792305,
      "completed": 389,
      "seeders": 40,
      "leechers": 0,
      "numComments": 0,
      "tags": [
        "Drama",
        "FREELEECH",
        "History"
      ],
      "new": false,
      "imdbID": "tt31121364",
      "rating": 7.7,
      "genres": "Biography, Drama, History",
      "tvmazeID": "s74416",
      "igdbID": "",
      "animeID": "",
      "download_multiplier": 0,
      "commentsDisabled": 0
    },
    {
      "fid": "241658521",
      "filename": "The.Imitation.Game.2014.1080p.BRA.Blu-ray.AVC.DTS-HD.MA.5.1-Mpira.torrent",
      "name": "The Imitation Game 2014 1080p BRA Blu-ray AVC DTS-HD MA 5.1-Mpira",
      "addedTimestamp": "2025-12-09 19:51:48",
      "categoryID": 13,
      "size": 24752455136,
      "completed": 89,
      "seeders": 3,
      "leechers": 0,
      "numComments": 0,
      "tags": [
        "Biography",
        "Drama",
        "FREELEECH",
        "Thriller"
      ],
      "new": false,
      "imdbID": "tt2084970",
      "rating": 8,
      "genres": "Biography, Drama, Thriller",
      "tvmazeID": "",
      "igdbID": "",
      "animeID": "",
      "download_multiplier": 0,
      "commentsDisabled": 0
    }
  ],
  "facets": {
    "tags": {
      "name": "tags",
      "title": "Tags",
      "type": "field",
      "items": {
        "FREELEECH": 286329,
        "Drama": 104769,
        "Action": 64767,
        "Thriller": 56443,
        "comedy": 56142,
        "rar": 54491,
        "Adventure": 48279,
        "Crime": 41244,
        "nonscene": 35363,
        "Sci-Fi": 29541,
        "Fantasy": 27490,
        "Horror": 25895,
        "Mystery": 24882,
        "Romance": 21663,
        "Family": 15757,
        "Animation": 10958,
        "History": 9587,
        "Science-Fiction": 8791,
        "Biography": 7011,
        "War": 6501,
        "Documentary": 6022,
        "Sport": 4697,
        "Music": 4685,
        "Western": 4397,
        "supernatural": 3716,
        "Musical": 3393,
        "Children": 2632,
        "1080p": 2501,
        "ZMNT": 2437,
        "Sports": 2299,
        "Reality-TV": 2272,
        "foreign": 2151,
        "Role-playing (RPG)": 1754,
        "x265": 1699,
        "720p": 1558,
        "hevc": 1505,
        "Shooter": 1420,
        "simulator": 1265,
        "Anime": 1246,
        "nature": 1233,
        "Upscaled": 1230,
        "retro": 1170,
        "remux": 1144,
        "480p": 1120,
        "BluRay": 1101,
        "food": 1045,
        "Medical": 994,
        "Espionage": 986,
        "travel": 881,
        "Legal": 839,
        "Short": 833,
        "Indie": 741,
        "10bit": 718,
        "4k": 701,
        "Strategy": 695,
        "#BiTOR": 688,
        "2160p": 684,
        "Film-Noir": 656,
        "Slice of Life": 644,
        "xvid": 616,
        "dolby vision": 609,
        "Game-Show": 520,
        "Motorsport": 496,
        "Reality": 491,
        "Psychological": 481,
        "Racing": 477,
        "UHD": 417,
        "extreme-sport": 408,
        "aac": 404,
        "Original Keystone": 389,
        "english subtitles": 383,
        "DH": 354,
        "Fighting": 352,
        "HDR10": 346,
        "ISO": 332,
        "DIY": 330,
        "mecha": 330,
        "#HEVC.DV": 324,
        "1080p BluRay": 315,
        "german": 292,
        "Tactical": 288,
        "DLC": 282,
        "ELiTE": 282,
        "GuyZo": 277,
        "hybrid": 274,
        "DTS-HD": 272,
        "#HEVC.HDR10": 270,
        "tt6758316": 269,
        "Ecchi": 268,
        "Dublado": 267,
        "car-action": 265,
        "HD": 261,
        "PHOCiS": 261,
        "GOG-DRM Free": 260,
        "snooker": 258,
        "Amber": 248,
        "1080p.Web-DL": 245,
        "3D": 244,
        "WEB-DL": 238,
        "PC": 237,
        "Hack and slash/Beat em up": 226,
        "webdl": 220,
        "Talk-Show": 218,
        "Turn-based strategy (TBS)": 217,
        "Adult": 215,
        "HDR": 213,
        "Puzzle": 212,
        "wwe": 212,
        "anime hd": 209,
        "x264": 205,
        "Platform": 203,
        "QxR": 198,
        "RUBiK": 195,
        "Hack and slash/Beat 'em up": 189,
        "complete": 184,
        "Wrestling": 183,
        "scifi": 182,
        "DV": 177,
        "Real Time Strategy (RTS)": 176,
        "DVDRip": 173,
        "tv series": 169,
        "#DOLBY.VISION.MP4": 168,
        "cricket": 167,
        "udemy": 157,
        "blu-ray": 156,
        "animehd": 155,
        "undisclosed": 154,
        "data lass": 153,
        "tt3622158": 150,
        "Fenix": 149,
        "WWF": 149,
        "nordic-sub": 148,
        "Dual Audio": 146,
        "HDR10+": 146,
        "atmos": 144,
        "#BluRay": 139,
        "Arcade": 138,
        "dts-hd ma": 136,
        "#HEVC.HDR10+": 130,
        "TrueHD atmos": 130,
        "OFT": 121,
        "5.1": 120,
        "T0PAZ": 120,
        "deef": 115,
        "TiPEX": 111,
        "DDP": 110,
        "VR": 108,
        "FraMeSToR": 106,
        "Snooker HD": 106,
        "1080pHD": 104,
        "TrueHD": 104,
        "#HEVC.DV.HDR10+": 102,
        "snooker 2024": 102,
        "HEVCode": 100,
        "3dprint": 98,
        "7.1": 97,
        "News": 96,
        "cricket highlights": 94,
        "Backport": 90,
        "PACK": 87,
        "Sitcom": 87,
        "TV Show": 84,
        "flight": 83,
        "fzhd": 83,
        "#SHD.TiTAN": 81,
        "DDP5.1": 81,
        "HDR10Plus": 80,
        "encode": 80,
        "monster": 80,
        "Snooker 2025": 79,
        "Webrip": 78,
        "720p.Web-DL": 76,
        "2.0": 75,
        "rock": 75,
        "criterion": 74,
        "2021": 72,
        "BBC": 71,
        "Creature": 71,
        "2022": 70,
        "Core": 70,
        "DTS-HDMA": 70,
        "F1": 70,
        "HDTV": 70,
        "Cricket HD": 69,
        "Type R": 68,
        "Boxset": 67,
        "nordic": 67,
        "Kaiju": 65,
        "DVD": 63,
        "AV1": 61,
        "DoVi": 61,
        "NoRBiT": 61,
        "WEB-RIP": 61,
        "DTS": 60,
        "Repack": 60,
        "MP4": 59,
        "8RM": 58,
        "Japanese": 58,
        "Cricket 2025": 57,
        "MWR": 57
      }
    },
    "size": {
      "name": "size",
      "title": "Size",
      "type": "range",
      "items": {
        "[0 TO 786432000]": {
          "count": 508,
          "label": "0MB - 750MB"
        },
        "[786432000 TO 1610612736]": {
          "count": 2383,
          "label": "750MB - 1.5GB"
        },
        "[1610612736 TO 4831838208]": {
          "count": 19405,
          "label": "1.5GB - 4.5GB"
        },
        "[4831838208 TO 16106127360]": {
          "count": 51622,
          "label": "4.5GB - 15GB"
        },
        "[16106127360 TO *]": {
          "count": 212411,
          "label": "More than 15GB"
        }
      }
    },
    "added": {
      "name": "added",
      "title": "Added",
      "type": "range",
      "items": {
        "[NOW/MINUTE-24HOURS TO NOW/MINUTE+1MINUTE]": {
          "count": 110,
          "label": "Last 24hrs"
        },
        "[NOW/MINUTE-48HOURS TO NOW/MINUTE+1MINUTE]": {
          "count": 235,
          "label": "Last 48hrs"
        },
        "[NOW/MINUTE-72HOURS TO NOW/MINUTE+1MINUTE]": {
          "count": 412,
          "label": "Last 72hrs"
        },
        "[NOW/HOUR-7DAYS TO NOW/HOUR+1HOUR]": {
          "count": 1019,
          "label": "Last week"
        },
        "[NOW/HOUR-14DAYS TO NOW/HOUR+1HOUR]": {
          "count": 1970,
          "label": "Last 2 weeks"
        },
        "[NOW/HOUR-1MONTH TO NOW/HOUR+1HOUR]": {
          "count": 3911,
          "label": "Last month"
        }
      }
    },
    "seeders": {
      "name": "seeders",
      "title": "Seeders",
      "type": "range",
      "items": {
        "[0 TO 50]": {
          "count": 271012,
          "label": "0 - 50"
        },
        "[51 TO 200]": {
          "count": 14082,
          "label": "51 - 200"
        },
        "[201 TO *]": {
          "count": 1235,
          "label": "More than 200"
        }
      }
    },
    "name": {
      "name": "name",
      "title": "HD Resolution",
      "type": "range",
      "items": {
        "720p": {
          "count": 22497,
          "label": "720p"
        },
        "1080p": {
          "count": 123415,
          "label": "1080p"
        },
        "2160p": {
          "count": 50583,
          "label": "2160p"
        }
      }
    }
  },
  "facetswoc": {
    "categoryID": {
      "name": "categoryID",
      "title": "CategoryID",
      "type": "field",
      "items": {
        "27": 118100,
        "13": 55551,
        "47": 38934,
        "36": 16402,
        "14": 10518,
        "44": 10048,
        "31": 7097,
        "17": 5587,
        "34": 5262,
        "15": 4643,
        "32": 3143,
        "33": 1702,
        "16": 1552,
        "38": 1530,
        "39": 1522,
        "29": 1151,
        "37": 679,
        "48": 524,
        "46": 476,
        "45": 368,
        "23": 298,
        "49": 233,
        "25": 206,
        "42": 131,
        "21": 117,
        "28": 112,
        "24": 96,
        "40": 85,
        "19": 65,
        "43": 41,
        "12": 40,
        "11": 32,
        "20": 31,
        "30": 14,
        "22": 12,
        "8": 9,
        "18": 9,
        "9": 7,
        "26": 2
      }
    }
  },
  "order": "desc",
  "orderBy": "added",
  "page": 368,
  "perPage": 35,
  "lastBrowseTime": "1773598293",
  "userTimeZone": "UTC"
}